setga/select_subset.py
setga/utils.py
setga-2.0.dist-info/LICENSE
setga-2.0.dist-info/METADATA
setga-2.0.dist-info/WHEEL
setga-2.0.dist-info/top_level.txt
setga-2.0.dist-info/RECORD
